setup.py
countdown_slackbot/__init__.py
countdown_slackbot/__main__.py
countdown_slackbot/bot.py
countdown_slackbot/numbers.py
countdown_slackbot.egg-info/PKG-INFO
countdown_slackbot.egg-info/SOURCES.txt
countdown_slackbot.egg-info/dependency_links.txt
countdown_slackbot.egg-info/requires.txt
countdown_slackbot.egg-info/top_level.txt
countdown_slackbot/tests/__init__.py
countdown_slackbot/tests/test_numbers_game.py