Metadata-Version: 1.0
Name: countdown-slackbot
Version: 0.0.2
Summary: A slackbot that plays countdown
Home-page: https://github.com/sujaymansingh/countdown-slackbot
Author: Sujay Mansingh
Author-email: sujay.mansingh@gmail.com
License: LICENSE.txt
Platform: UNKNOWN
